CHANGES.rst
INSTALL.rst
LICENSE.txt
MANIFEST.in
README.rst
setup.py
frappedata/__init__.py
frappedata/dataset.py
frappedata.egg-info/PKG-INFO
frappedata.egg-info/SOURCES.txt
frappedata.egg-info/dependency_links.txt
frappedata.egg-info/not-zip-safe
frappedata.egg-info/requires.txt
frappedata.egg-info/top_level.txt
frappedata/data/photrates_used.csv
frappedata/data/species_used.csv
frappedata/data/extracts/BIOGENIC.csv
frappedata/data/extracts/COMMERCE_CITY.csv
frappedata/data/extracts/DENVER.csv
frappedata/data/extracts/DENVER_AVE.csv
frappedata/data/extracts/DENVER_O&G.csv
frappedata/data/extracts/DENVER_UPSLOPE.csv
frappedata/data/extracts/FOOTHILLS_BKGD.csv
frappedata/data/extracts/RIFLE.csv
frappedata/data/extracts/UINTAH.csv
frappedata/data/extracts/UINTAH_NOX.csv
frappedata/data/extracts/WELD.csv
frappedata/data/extracts/WELD_AVE.csv
frappedata/data/extracts/WELD_LOWALK.csv
frappedata/data/extracts/WELD_NOX.csv
frappedata/data/extracts/WELD_UPSLOPE.csv
frappedata/data/extracts/stub.ict